gorillaml/__init__.py
gorillaml/db.py
gorillaml/form.py
gorillaml/lab.py
gorillaml/widget.py
gorillaml/static/css/adminlte.css
gorillaml/static/css/adminlte.min.css
gorillaml/static/css/codemirror.css
gorillaml/static/css/custom.css
gorillaml/static/css/fonts.css
gorillaml/static/css/ionicons.min.css
gorillaml/static/css/prism-live.css
gorillaml/static/css/prism.css
gorillaml/static/fonts/6xK1dSBYKcSV-LCoeQqfX1RYOo3qPZ7jsDJT9g.woff2
gorillaml/static/fonts/6xK1dSBYKcSV-LCoeQqfX1RYOo3qPZ7ksDJT9g.woff2
gorillaml/static/fonts/6xK1dSBYKcSV-LCoeQqfX1RYOo3qPZ7nsDI.woff2
gorillaml/static/fonts/6xK1dSBYKcSV-LCoeQqfX1RYOo3qPZ7osDJT9g.woff2
gorillaml/static/fonts/6xK1dSBYKcSV-LCoeQqfX1RYOo3qPZ7psDJT9g.woff2
gorillaml/static/fonts/6xK1dSBYKcSV-LCoeQqfX1RYOo3qPZ7qsDJT9g.woff2
gorillaml/static/fonts/6xK1dSBYKcSV-LCoeQqfX1RYOo3qPZ7rsDJT9g.woff2
gorillaml/static/fonts/6xK3dSBYKcSV-LCoeQqfX1RYOo3qN67lqDY.woff2
gorillaml/static/fonts/6xK3dSBYKcSV-LCoeQqfX1RYOo3qNK7lqDY.woff2
gorillaml/static/fonts/6xK3dSBYKcSV-LCoeQqfX1RYOo3qNa7lqDY.woff2
gorillaml/static/fonts/6xK3dSBYKcSV-LCoeQqfX1RYOo3qNq7lqDY.woff2
gorillaml/static/fonts/6xK3dSBYKcSV-LCoeQqfX1RYOo3qO67lqDY.woff2
gorillaml/static/fonts/6xK3dSBYKcSV-LCoeQqfX1RYOo3qOK7l.woff2
gorillaml/static/fonts/6xK3dSBYKcSV-LCoeQqfX1RYOo3qPK7lqDY.woff2
gorillaml/static/fonts/6xKydSBYKcSV-LCoeQqfX1RYOo3ig4vwkxduz8A.woff2
gorillaml/static/fonts/6xKydSBYKcSV-LCoeQqfX1RYOo3ig4vwlBduz8A.woff2
gorillaml/static/fonts/6xKydSBYKcSV-LCoeQqfX1RYOo3ig4vwlxdu.woff2
gorillaml/static/fonts/6xKydSBYKcSV-LCoeQqfX1RYOo3ig4vwmBduz8A.woff2
gorillaml/static/fonts/6xKydSBYKcSV-LCoeQqfX1RYOo3ig4vwmRduz8A.woff2
gorillaml/static/fonts/6xKydSBYKcSV-LCoeQqfX1RYOo3ig4vwmhduz8A.woff2
gorillaml/static/fonts/6xKydSBYKcSV-LCoeQqfX1RYOo3ig4vwmxduz8A.woff2
gorillaml/static/fonts/6xKydSBYKcSV-LCoeQqfX1RYOo3ik4zwkxduz8A.woff2
gorillaml/static/fonts/6xKydSBYKcSV-LCoeQqfX1RYOo3ik4zwlBduz8A.woff2
gorillaml/static/fonts/6xKydSBYKcSV-LCoeQqfX1RYOo3ik4zwlxdu.woff2
gorillaml-0.2.0.dist-info/LICENSE
gorillaml-0.2.0.dist-info/METADATA
gorillaml-0.2.0.dist-info/WHEEL
gorillaml-0.2.0.dist-info/entry_points.txt
gorillaml-0.2.0.dist-info/top_level.txt
gorillaml-0.2.0.dist-info/RECORD
