Metadata-Version: 2.1
Name: gorillaml
Version: 0.2.0
Summary: This is the application which allow individual, organization, developer, publisher to manage, publish, monitor webservices, machine learning api, custom forms and many more active development very easily.
Home-page: https://www.gorillaml.com
Author: Washim Ahmed
Author-email: washim.ahmed@gmail.com
License: MIT license
Platform: UNKNOWN
Classifier: Programming Language :: Python :: 3
Classifier: License :: OSI Approved :: MIT License
Classifier: Operating System :: OS Independent
Requires-Python: >=3
Requires-Dist: Flask
Requires-Dist: Flask-WTF
Requires-Dist: WTForms
Requires-Dist: Werkzeug
Requires-Dist: Flask-Cors
Requires-Dist: SQLAlchemy
Requires-Dist: click
Requires-Dist: watchdog
Requires-Dist: beautifulsoup4
Requires-Dist: requests
Requires-Dist: mpld3
Requires-Dist: scipy
Requires-Dist: pandas
Requires-Dist: numpy
Requires-Dist: matplotlib
Requires-Dist: bokeh
Requires-Dist: PyQt5 (<5.13)
Requires-Dist: pyqtwebengine (<5.13)
